potatodata/__init__.py
potatodata/category.py
potatodata/db.py
potatodata/detail.py
potatodata/find.py
potatodata/make.py
potatodata/modify.py
potatodata/page.py
potatodata/plan.py
potatodata/potato.py
potatodata/remove.py
potatodata/version.py
potatotodo-1.1.4.dist-info/DESCRIPTION.rst
potatotodo-1.1.4.dist-info/METADATA
potatotodo-1.1.4.dist-info/RECORD
potatotodo-1.1.4.dist-info/WHEEL
potatotodo-1.1.4.dist-info/entry_points.txt
potatotodo-1.1.4.dist-info/metadata.json
potatotodo-1.1.4.dist-info/top_level.txt
