Metadata-Version: 2.0
Name: potatotodo
Version: 1.1.4
Summary: This is very usual todo-list
Home-page: https://github.com/bean3/to-do-list
Author: Team_potato
Author-email: UNKNOWN
License: UNKNOWN
Platform: UNKNOWN
Classifier: Programming Language :: Python :: 3.6
Requires-Python: >=3.6
Requires-Dist: click
Requires-Dist: colorama
